main.py
ast_tool_py-0.27.8.dist-info/licenses/LICENSE
ast_tool_py-0.27.8.dist-info/METADATA
ast_tool_py-0.27.8.dist-info/WHEEL
ast_tool_py-0.27.8.dist-info/entry_points.txt
ast_tool_py-0.27.8.dist-info/top_level.txt
ast_tool_py-0.27.8.dist-info/RECORD
