Metadata-Version: 2.4
Name: ast-tool-py
Version: 0.27.8
Summary: Asterix data processing tool
Author-email: Zoran Bošnjak <zoran.bosnjak@via.si>
License-Expression: MIT
Project-URL: Homepage, https://github.com/zoranbosnjak/asterix-tool/tree/master/ast-tool-py#readme
Project-URL: Bug Tracker, https://github.com/zoranbosnjak/ast-tool/issues
Keywords: asterix,eurocontrol,radar
Classifier: Programming Language :: Python :: 3
Classifier: Operating System :: OS Independent
Requires-Python: >=3.8
License-File: LICENSE
Requires-Dist: typing_extensions; python_version < "3.10"
Requires-Dist: scapy
Requires-Dist: libasterix
Dynamic: license-file
